{"expireTime":9007200834648306000,"key":"gatsby-plugin-mdx-entire-payload-33f72a7c1f9f6b2971bfca2470b14484-/react-elastic-carousel","val":{"mdast":{"type":"root","children":[{"type":"import","value":"import DefaultLayout from \"C:/Users/sagiv/github clones/react-elastic-carousel/node_modules/gatsby-theme-docz/src/base/Layout.js\"","position":{"start":{"line":3,"column":1,"offset":2},"end":{"line":3,"column":130,"offset":131},"indent":[]}},{"type":"export","default":true,"value":"export default DefaultLayout","position":{"start":{"line":5,"column":1,"offset":133},"end":{"line":5,"column":29,"offset":161},"indent":[]}},{"type":"import","value":"import {Playground, Props } from 'docz';\nimport Carousel from 'react-elastic-carousel';\nimport Item from '../components/SimpleItem';","position":{"start":{"line":8,"column":1,"offset":165},"end":{"line":10,"column":45,"offset":299},"indent":[1,1]}},{"type":"heading","depth":1,"children":[{"type":"text","value":"Getting started","position":{"start":{"line":12,"column":3,"offset":305},"end":{"line":12,"column":18,"offset":320},"indent":[]}}],"position":{"start":{"line":12,"column":1,"offset":303},"end":{"line":12,"column":18,"offset":320},"indent":[]}},{"type":"heading","depth":2,"children":[{"type":"text","value":"install","position":{"start":{"line":14,"column":4,"offset":327},"end":{"line":14,"column":11,"offset":334},"indent":[]}}],"position":{"start":{"line":14,"column":1,"offset":324},"end":{"line":14,"column":11,"offset":334},"indent":[]}},{"type":"code","lang":null,"meta":null,"value":"npm install react-elastic-carousel","position":{"start":{"line":15,"column":1,"offset":336},"end":{"line":17,"column":4,"offset":380},"indent":[1,1]}},{"type":"heading","depth":2,"children":[{"type":"text","value":"Import","position":{"start":{"line":19,"column":4,"offset":387},"end":{"line":19,"column":10,"offset":393},"indent":[]}}],"position":{"start":{"line":19,"column":1,"offset":384},"end":{"line":19,"column":10,"offset":393},"indent":[]}},{"type":"code","lang":null,"meta":null,"value":"import Carousel from 'react-elastic-carousel'","position":{"start":{"line":20,"column":1,"offset":395},"end":{"line":22,"column":4,"offset":450},"indent":[1,1]}},{"type":"heading","depth":2,"children":[{"type":"text","value":"play","position":{"start":{"line":24,"column":4,"offset":457},"end":{"line":24,"column":8,"offset":461},"indent":[]}}],"position":{"start":{"line":24,"column":1,"offset":454},"end":{"line":24,"column":9,"offset":462},"indent":[]}},{"type":"jsx","value":"<Playground >\n  <Carousel itemsToShow={1}>\n    <Item>1</Item>\n    <Item>2</Item>\n    <Item>3</Item>\n    <Item>4</Item>\n    <Item>5</Item>\n    <Item>6</Item>\n  </Carousel>\n</Playground>","position":{"start":{"line":26,"column":1,"offset":466},"end":{"line":35,"column":14,"offset":659},"indent":[1,1,1,1,1,1,1,1,1]}},{"type":"heading","depth":2,"children":[{"type":"text","value":"Props","position":{"start":{"line":37,"column":4,"offset":666},"end":{"line":37,"column":9,"offset":671},"indent":[]}}],"position":{"start":{"line":37,"column":1,"offset":663},"end":{"line":37,"column":9,"offset":671},"indent":[]}},{"type":"jsx","value":"<Props of={Carousel} />","position":{"start":{"line":39,"column":1,"offset":675},"end":{"line":39,"column":24,"offset":698},"indent":[]}},{"type":"export","value":"export const _frontmatter = {}","position":{"start":{"line":41,"column":1,"offset":700},"end":{"line":41,"column":31,"offset":730},"indent":[]}}],"position":{"start":{"line":1,"column":1,"offset":0},"end":{"line":41,"column":31,"offset":730}}},"scopeImports":[],"scopeIdentifiers":[],"rawMDXOutput":"/* @jsx mdx */\nimport { mdx } from '@mdx-js/react';\n/* @jsx mdx */\nimport DefaultLayout from \"C:/Users/sagiv/github clones/react-elastic-carousel/node_modules/gatsby-theme-docz/src/base/Layout.js\"\nimport {Playground, Props } from 'docz';\nimport Carousel from 'react-elastic-carousel';\nimport Item from '../components/SimpleItem';\nexport const _frontmatter = {};\nconst makeShortcode = name => function MDXDefaultShortcode(props) {\n  console.warn(\"Component \" + name + \" was not imported, exported, or provided by MDXProvider as global scope\")\n  return <div {...props}/>\n};\n\nconst layoutProps = {\n  _frontmatter\n};\nconst MDXLayout = DefaultLayout\nexport default function MDXContent({\n  components,\n  ...props\n}) {\n  return <MDXLayout {...layoutProps} {...props} components={components} mdxType=\"MDXLayout\">\n\n\n\n    <h1 {...{\n      \"id\": \"getting-started\"\n    }}>{`Getting started`}</h1>\n    <h2 {...{\n      \"id\": \"install\"\n    }}>{`install`}</h2>\n    <pre><code parentName=\"pre\" {...{}}>{`npm install react-elastic-carousel\n`}</code></pre>\n    <h2 {...{\n      \"id\": \"import\"\n    }}>{`Import`}</h2>\n    <pre><code parentName=\"pre\" {...{}}>{`import Carousel from 'react-elastic-carousel'\n`}</code></pre>\n    <h2 {...{\n      \"id\": \"play\"\n    }}>{`play`}</h2>\n    <Playground __position={0} __code={'<Carousel itemsToShow={1}>\\n  <Item>1</Item>\\n  <Item>2</Item>\\n  <Item>3</Item>\\n  <Item>4</Item>\\n  <Item>5</Item>\\n  <Item>6</Item>\\n</Carousel>'} __scope={{\n      props,\n      DefaultLayout,\n      Playground,\n      Props,\n      Carousel,\n      Item,\n      DefaultLayout,\n      _frontmatter\n    }} mdxType=\"Playground\">\n  <Carousel itemsToShow={1} mdxType=\"Carousel\">\n    <Item mdxType=\"Item\">1</Item>\n    <Item mdxType=\"Item\">2</Item>\n    <Item mdxType=\"Item\">3</Item>\n    <Item mdxType=\"Item\">4</Item>\n    <Item mdxType=\"Item\">5</Item>\n    <Item mdxType=\"Item\">6</Item>\n  </Carousel>\n    </Playground>\n    <h2 {...{\n      \"id\": \"props\"\n    }}>{`Props`}</h2>\n    <Props of={Carousel} mdxType=\"Props\" />\n\n    </MDXLayout>;\n}\n\n;\nMDXContent.isMDXComponent = true;"}}